niacin/__init__.py
niacin/py.typed
niacin/augment/__init__.py
niacin/augment/randaugment.py
niacin/data/contractions.json
niacin/data/hypernyms.json
niacin/data/hyponyms.json
niacin/data/misspellings.json
niacin/data/neighbors.json
niacin/data/synonyms.json
niacin/text/__init__.py
niacin/text/compat/__init__.py
niacin/text/compat/pytorch.py
niacin/text/en/__init__.py
niacin/text/en/char.py
niacin/text/en/sentence.py
niacin/text/en/word.py
niacin/timeseries/__init__.py
niacin/timeseries/freq.py
niacin/timeseries/time.py
niacin-0.5.2.dist-info/LICENSE
niacin-0.5.2.dist-info/METADATA
niacin-0.5.2.dist-info/WHEEL
niacin-0.5.2.dist-info/top_level.txt
niacin-0.5.2.dist-info/RECORD
