Metadata-Version: 2.1
Name: niacin
Version: 0.5.2
Requires-Python: >=3.6
License-File: LICENSE
Requires-Dist: nltk (>=3.0)
Requires-Dist: regex
Requires-Dist: scipy (>=1.0.0)
Provides-Extra: all
Requires-Dist: fairseq ; extra == 'all'
Requires-Dist: fastbpe ; extra == 'all'
Requires-Dist: pandas ; extra == 'all'
Requires-Dist: sacremoses ; extra == 'all'
Requires-Dist: torch ; extra == 'all'
Requires-Dist: torchtext ; extra == 'all'
Provides-Extra: backtranslate
Requires-Dist: fairseq ; extra == 'backtranslate'
Requires-Dist: fastbpe ; extra == 'backtranslate'
Requires-Dist: sacremoses ; extra == 'backtranslate'
Requires-Dist: torch ; extra == 'backtranslate'
Provides-Extra: torch
Requires-Dist: pandas ; extra == 'torch'
Requires-Dist: torch ; extra == 'torch'
Requires-Dist: torchtext ; extra == 'torch'
